wish_knowledge_loader-0.6.28.dist-info/LICENSE
wish_knowledge_loader-0.6.28.dist-info/METADATA
wish_knowledge_loader-0.6.28.dist-info/WHEEL
wish_knowledge_loader-0.6.28.dist-info/entry_points.txt
wish_knowledge_loader/__init__.py
wish_knowledge_loader/cli.py
wish_knowledge_loader/nodes/__init__.py
wish_knowledge_loader/nodes/document_loader.py
wish_knowledge_loader/nodes/repo_cloner.py
wish_knowledge_loader/nodes/vector_store.py
wish_knowledge_loader/utils/__init__.py
wish_knowledge_loader/utils/logging_utils.py
wish_knowledge_loader/utils/path_utils.py
wish_knowledge_loader-0.6.28.dist-info/RECORD
