Metadata-Version: 2.1
Name: wish-knowledge-loader
Version: 0.6.28
Summary: Knowledge loader for wish
Keywords: wish,llm,ai,knowledge,rag
Author-Email: Security & Development Lab <lay.sakura+secdevlab@gmail.com>
Maintainer-Email: Sho Nakatani <lay.sakura@gmail.com>
License:                     GNU AFFERO GENERAL PUBLIC LICENSE
Classifier: Development Status :: 4 - Beta
Classifier: Intended Audience :: Developers
Classifier: Programming Language :: Python :: 3
Classifier: Programming Language :: Python :: 3.10
Classifier: Programming Language :: Python :: 3.11
Classifier: Programming Language :: Python :: 3.12
Classifier: Programming Language :: Python :: 3.13
Classifier: Topic :: Software Development :: Libraries
Project-URL: Homepage, https://github.com/SecDev-Lab/wish
Project-URL: Documentation, https://github.com/SecDev-Lab/wish
Project-URL: Repository, https://github.com/SecDev-Lab/wish.git
Project-URL: Issues, https://github.com/SecDev-Lab/wish/issues
Requires-Python: >=3.10
Requires-Dist: wish-models==0.6.28
Requires-Dist: click>=8.1.7
Requires-Dist: langchain>=0.1.0
Requires-Dist: langchain-community>=0.1.0
Requires-Dist: langchain-openai>=0.1.0
Requires-Dist: chromadb>=0.4.22
Requires-Dist: pydantic>=2.5.0
Requires-Dist: pydantic-settings>=2.1.0
